openaleph/__init__.py
openaleph/api.py
openaleph/cli.py
openaleph/crawldir.py
openaleph/errors.py
openaleph/fetchdir.py
openaleph/settings.py
openaleph/util.py
openaleph_client-1.1.3.dist-info/licenses/LICENSE
openaleph_client-1.1.3.dist-info/METADATA
openaleph_client-1.1.3.dist-info/WHEEL
openaleph_client-1.1.3.dist-info/entry_points.txt
openaleph_client-1.1.3.dist-info/top_level.txt
openaleph_client-1.1.3.dist-info/RECORD
