Metadata-Version: 2.4
Name: openaleph-client
Version: 1.1.3
Summary: Python client for the OpenAleph data API
Author-email: Data and Research Center - DARC <hi@dataresearchcenter.org>
License: MIT License
Project-URL: Repository, https://github.com/dataresearchcenter/opal-client
Classifier: Programming Language :: Python :: 3
Classifier: License :: OSI Approved :: MIT License
Classifier: Operating System :: OS Independent
Requires-Python: >=3.8
License-File: LICENSE
Requires-Dist: banal<2.0.0,>=1.0.1
Requires-Dist: pyyaml<7.0.0,>=5.0.0
Requires-Dist: requests<3.0.0,>=2.21.0
Requires-Dist: requests_toolbelt<2.0.0,>=1.0.0
Requires-Dist: urllib3<2.0.0,>=1.26.0
Requires-Dist: click<9.0,>=7.0
Provides-Extra: dev
Requires-Dist: mypy; extra == "dev"
Requires-Dist: wheel; extra == "dev"
Requires-Dist: pytest; extra == "dev"
Requires-Dist: pytest-mock>=1.10.0; extra == "dev"
Requires-Dist: types-requests; extra == "dev"
Requires-Dist: types-setuptools; extra == "dev"
Dynamic: license-file
